historical_binance.py
historical_binance-0.1.7.8.dist-info/LICENSE
historical_binance-0.1.7.8.dist-info/METADATA
historical_binance-0.1.7.8.dist-info/WHEEL
historical_binance-0.1.7.8.dist-info/top_level.txt
historical_binance-0.1.7.8.dist-info/RECORD
