Metadata-Version: 2.1
Name: historical_binance
Version: 0.1.7.8
Summary: A very fast downloader for Binance historical data
Author: Denkik
Classifier: Programming Language :: Python :: 3
Classifier: Operating System :: OS Independent
Requires-Python: >=3.6
License-File: LICENSE
